{"startedAt":1629272265490,"id":"0Vl1HKdYR5ADiSDmLeqkFQ","suite":"Sirion URL Test","title":"Sirion Login & Version Check | {\"login\":\"karuna_user\",\"pass\":\"admin123\"}","file":"/home/naveenkg/Documents/SirionUI/Sirion_test.js","steps":[{"id":"DNL8NWSedz1kW0GidiWj2","testId":"0Vl1HKdYR5ADiSDmLeqkFQ","at":277,"duration":234,"actor":"I","humanized":"clear cookie","humanizedArgs":"","status":"success","name":"clearCookie","args":[],"store":{"debugMode":false,"actor":{}},"logs":[],"stack":{"stackFrameInTest":"    at Test.<anonymous> (/home/naveenkg/Documents/SirionUI/Sirion_test.js:8:7)","stackFrameOfStep":"    at Step.setTrace (/home/naveenkg/Documents/SirionUI/node_modules/codeceptjs/lib/step.js:46:11)"},"startedAt":1629272265533,"snapshot":{"hasScreenshot":false,"hasSnapshot":true,"id":"DNL8NWSedz1kW0GidiWj2","pageUrl":"about:blank","pageTitle":"","sourceContentType":"html","height":1050,"width":1680}},{"id":"st5LOpx9qnyBCcor7eLRu","testId":"0Vl1HKdYR5ADiSDmLeqkFQ","at":6726,"duration":6447,"actor":"I","humanized":"go to","humanizedArgs":"\"https://testwu.sirioninc.net\"","status":"success","name":"goTo","args":["https://testwu.sirioninc.net"],"store":{"debugMode":false,"actor":{}},"logs":[],"stack":{"stackFrameInTest":"    at Test.<anonymous> (/home/naveenkg/Documents/SirionUI/Sirion_test.js:9:7)","stackFrameOfStep":"    at Step.setTrace (/home/naveenkg/Documents/SirionUI/node_modules/codeceptjs/lib/step.js:46:11)"},"startedAt":1629272265769,"snapshot":{"hasScreenshot":false,"hasSnapshot":true,"id":"st5LOpx9qnyBCcor7eLRu","pageUrl":"https://testwu.sirioninc.net/ux/login/","pageTitle":"SirionLabs","sourceContentType":"html","height":1050,"width":1680}},{"id":"rHyQFUlOg5xStipinwp_3","testId":"0Vl1HKdYR5ADiSDmLeqkFQ","at":8063,"duration":1332,"actor":"I","humanized":"fill","humanizedArgs":"\"Sirion ID\", \"karuna_user\"","status":"success","name":"fill","args":["Sirion ID","karuna_user"],"store":{"debugMode":false,"actor":{}},"logs":[],"stack":{"stackFrameInTest":"    at Test.<anonymous> (/home/naveenkg/Documents/SirionUI/Sirion_test.js:10:7)","stackFrameOfStep":"    at Step.setTrace (/home/naveenkg/Documents/SirionUI/node_modules/codeceptjs/lib/step.js:46:11)"},"startedAt":1629272272221,"snapshot":{"hasScreenshot":false,"hasSnapshot":true,"id":"rHyQFUlOg5xStipinwp_3","pageUrl":"https://testwu.sirioninc.net/ux/login/","pageTitle":"SirionLabs","sourceContentType":"html","height":1050,"width":1680}},{"id":"FMBIxQelP8ctEmXwChjrA","testId":"0Vl1HKdYR5ADiSDmLeqkFQ","at":9378,"duration":1309,"actor":"I","humanized":"fill","humanizedArgs":"\"Password\", \"admin123\"","status":"success","name":"fill","args":["Password","admin123"],"store":{"debugMode":false,"actor":{}},"logs":[],"stack":{"stackFrameInTest":"    at Test.<anonymous> (/home/naveenkg/Documents/SirionUI/Sirion_test.js:11:7)","stackFrameOfStep":"    at Step.setTrace (/home/naveenkg/Documents/SirionUI/node_modules/codeceptjs/lib/step.js:46:11)"},"startedAt":1629272273559,"snapshot":{"hasScreenshot":false,"hasSnapshot":true,"id":"FMBIxQelP8ctEmXwChjrA","pageUrl":"https://testwu.sirioninc.net/ux/login/","pageTitle":"SirionLabs","sourceContentType":"html","height":1050,"width":1680}},{"id":"53Fuquky5ZITNho4liqMb","testId":"0Vl1HKdYR5ADiSDmLeqkFQ","at":10328,"duration":944,"actor":"I","humanized":"press","humanizedArgs":"\"Enter\"","status":"success","name":"press","args":["Enter"],"store":{"debugMode":false,"actor":{}},"logs":[],"stack":{"stackFrameInTest":"    at Test.<anonymous> (/home/naveenkg/Documents/SirionUI/Sirion_test.js:12:7)","stackFrameOfStep":"    at Step.setTrace (/home/naveenkg/Documents/SirionUI/node_modules/codeceptjs/lib/step.js:46:11)"},"startedAt":1629272274874,"snapshot":{"hasScreenshot":false,"hasSnapshot":true,"id":"53Fuquky5ZITNho4liqMb","pageUrl":"https://testwu.sirioninc.net/ux/login/","pageTitle":"SirionLabs","sourceContentType":"html","height":1050,"width":1680}},{"id":"rLn_hpbWM17YC6xwOrpwY","testId":"0Vl1HKdYR5ADiSDmLeqkFQ","at":17453,"duration":7119,"actor":"I","humanized":"see","humanizedArgs":"\"Version\", \"//body/div[@id='footer']/span[1]\"","status":"success","name":"see","args":["Version","//body/div[@id='footer']/span[1]"],"store":{"debugMode":false,"actor":{}},"logs":[],"stack":{"stackFrameInTest":"    at Test.<anonymous> (/home/naveenkg/Documents/SirionUI/Sirion_test.js:15:11)","stackFrameOfStep":"    at Step.setTrace (/home/naveenkg/Documents/SirionUI/node_modules/codeceptjs/lib/step.js:46:11)"},"startedAt":1629272275824,"snapshot":{"hasScreenshot":true,"hasSnapshot":true,"id":"rLn_hpbWM17YC6xwOrpwY","pageUrl":"https://testwu.sirioninc.net/ux/#/dashboard","pageTitle":"Welcome to SirionLabs","sourceContentType":"html","height":1050,"width":1680}},{"id":"SdCbqglqiCfj0fCDCrEJv","testId":"0Vl1HKdYR5ADiSDmLeqkFQ","at":22440,"duration":4981,"actor":"I","humanized":"grab text from","humanizedArgs":"\"//body/div[@id='footer']/span[1]\"","status":"success","name":"grabTextFrom","args":["//body/div[@id='footer']/span[1]"],"store":{"debugMode":false,"actor":{}},"logs":[],"stack":{"stackFrameInTest":"    at Test.<anonymous> (/home/naveenkg/Documents/SirionUI/Sirion_test.js:16:30)","stackFrameOfStep":"    at Step.setTrace (/home/naveenkg/Documents/SirionUI/node_modules/codeceptjs/lib/step.js:46:11)"},"startedAt":1629272282949,"snapshot":{"hasScreenshot":false,"hasSnapshot":true,"id":"SdCbqglqiCfj0fCDCrEJv","pageUrl":"https://testwu.sirioninc.net/ux/#/dashboard","pageTitle":"Welcome to SirionLabs","sourceContentType":"html","height":1050,"width":1680}},{"id":"YBTKxyLbh2XFqOOdeORjM","testId":"0Vl1HKdYR5ADiSDmLeqkFQ","at":23999,"duration":1494,"actor":"I","humanized":"execute script","humanizedArgs":"function () {\n        var terms = document.getElementById(\"acceptTerms\");\n        if (terms == null) {\n            return \"No terms of usage pop-up\";\n        } else {\n            return document.getElementById(\"acceptTerms\").click() || document.getElementById(\"postTermsUsage\").click();\n        }\n        if (I.see(\"Welcome to UX 2.0!\")) {\n            I.click(\"Close\")\n        }\n    }","status":"success","name":"executeScript","args":["function () {\n        var terms = document.getElementById(\"acceptTerms\");\n        if (terms == null) {\n            return \"No terms of usage pop-up\";\n        } else {\n            return document.getElementById(\"acceptTerms\").click() || document.getElementById(\"postTermsUsage\").click();\n        }\n        if (I.see(\"Welcome to UX 2.0!\")) {\n            I.click(\"Close\")\n        }\n    }"],"store":{"debugMode":false,"actor":{}},"logs":[],"stack":{"stackFrameInTest":"    at Test.<anonymous> (/home/naveenkg/Documents/SirionUI/Sirion_test.js:25:13)","stackFrameOfStep":"    at Step.setTrace (/home/naveenkg/Documents/SirionUI/node_modules/codeceptjs/lib/step.js:46:11)"},"startedAt":1629272287995,"snapshot":{"hasScreenshot":false,"hasSnapshot":true,"id":"YBTKxyLbh2XFqOOdeORjM","pageUrl":"https://testwu.sirioninc.net/ux/#/dashboard","pageTitle":"Welcome to SirionLabs","sourceContentType":"html","height":1050,"width":1680}}],"result":"passed","duration":24.002}